ItsAGramLive/ItsAGramLive.py
ItsAGramLive/__init__.py
ItsAGramLive-1.6.dist-info/LICENSE
ItsAGramLive-1.6.dist-info/METADATA
ItsAGramLive-1.6.dist-info/WHEEL
ItsAGramLive-1.6.dist-info/top_level.txt
ItsAGramLive-1.6.dist-info/RECORD
