Metadata-Version: 2.1
Name: ItsAGramLive
Version: 1.6
Summary: Its A Gram Live is a Python script that create a Instagram Live and provide you a rtmp server and stream key to streaming using sofwares like OBS-Studio.
Home-page: https://github.com/harrypython/itsagramlive
Author: Harry Python
Author-email: harrypython@protonmail.com
License: GPL-3.0
Project-URL: Example, https://github.com/harrypython/itsagramlive/blob/master/live_broadcast.py
Project-URL: Bug Reports, https://github.com/harrypython/itsagramlive/issues
Project-URL: Buy me a coffee, https://www.buymeacoffee.com/harrypython
Platform: UNKNOWN
Requires-Python: >=3.6
Requires-Dist: pyperclip (>=1.8.0)
Requires-Dist: requests (>=2.23.0)
Requires-Dist: Pillow (~=8.0.0)
